datetimeops/__init__.py
datetimeops/datetime_utils.py
datetimeops-1.0.6.dist-info/licenses/LICENSE
datetimeops-1.0.6.dist-info/METADATA
datetimeops-1.0.6.dist-info/WHEEL
datetimeops-1.0.6.dist-info/top_level.txt
datetimeops-1.0.6.dist-info/RECORD
