Metadata-Version: 2.4
Name: datetimeops
Version: 1.0.6
Summary: A lightweight Python library for date and time operations.
Home-page: https://github.com/roamingsaint/datetimeops
Author: Kanad Rishiraj (RoamingSaint)
Author-email: roamingsaint27@gmail.com
Classifier: Programming Language :: Python :: 3
Classifier: License :: OSI Approved :: MIT License
Classifier: Operating System :: OS Independent
Requires-Python: >=3.7
License-File: LICENSE
Requires-Dist: pytz
Requires-Dist: python-dateutil
Dynamic: author
Dynamic: author-email
Dynamic: classifier
Dynamic: description
Dynamic: description-content-type
Dynamic: home-page
Dynamic: license-file
Dynamic: requires-dist
Dynamic: requires-python
Dynamic: summary
